Metadata-Version: 1.0
Name: distributions-Ziwei
Version: 0.1
Summary: Gaussian distributions
Home-page: UNKNOWN
Author: UNKNOWN
Author-email: testemail@gmail.com
License: UNKNOWN
Platform: UNKNOWN
